{
  "textures": {
    "CityDistributionMask": "res:/dx9/model/worldobject/planet/terrestrial/citylight03_m.dds.0.png",
    "PolesGradient": "res:/dx9/model/worldobject/Planet/Gradient01_M.dds.0.png",
    "CityLight": "res:/dx9/model/worldobject/planet/terrestrial/citylight03_g.dds.0.png",
    "CityDistributionTexture": "res:/dx9/model/worldobject/planet/terrestrial/citylight03_uv.dds.0.png",
    "GroundScattering1": "res:/dx9/model/worldobject/Planet/Preset/TerrestrialScatterLight01_D.dds.0.png",
    "GroundScattering2": "res:/dx9/model/worldobject/Planet/Preset/TerrestrialScatterHue01_D.dds.0.png",
    "CloudsTexture": "res:/dx9/model/worldobject/planet/terrestrial/cloudsparse03_m.dds.0.png",
    "FillTexture": "res:/dx9/model/worldobject/planet/terrestrial/terrestrialdetail04_p.dds.0.png",
    "CloudCapTexture": "res:/dx9/model/worldobject/planet/terrestrial/cloudsparsecap03_m.dds.0.png"
  },
  "settings": {
    "FillTint": [
      0.69384765625,
      0.67041015625,
      0.64306640625,
      1
    ],
    "CityLightColor": [
      0.71728515625,
      0.8701171875,
      0.90185546875,
      1
    ],
    "WaterColor": [
      0.058807373046875,
      0.0980224609375,
      0.1058349609375,
      1
    ],
    "DetailFactors": [
      4,
      1.0634765625,
      0,
      0
    ],
    "VegetationTint": [
      0.599609375,
      0.62744140625,
      0.615234375,
      1
    ],
    "mountainTint": [
      0.443115234375,
      0.462646484375,
      0.443115234375,
      1
    ],
    "MiscFactors": [
      0.0382080078125,
      0.25732421875,
      0,
      0
    ],
    "SharpnessFactors": [
      5.046875,
      4.0390625,
      6.08203125,
      0.01116180419921875
    ],
    "CloudsFactors": [
      0.360595703125,
      0.94580078125,
      1.9111328125,
      1
    ],
    "CoverageFactors": [
      0.63427734375,
      0.2215576171875,
      0.056884765625,
      0.49560546875
    ],
    "shallowWaterColor": [
      0.3056640625,
      0.356689453125,
      0.356689453125,
      1
    ],
    "EquatorTint": [
      0.462646484375,
      0.462646484375,
      0.462646484375,
      1
    ],
    "AtmosphereFactors": [
      1.01953125,
      0.04998779296875,
      299.75,
      0
    ],
    "wavelengthsMicroMeters": [
      0.572265625,
      0.591796875,
      0.611328125,
      1
    ],
    "ScatteringFactors": [
      0.00499725341796875,
      0.0019989013671875,
      20,
      0
    ],
    "CloudsColor": [
      0.96044921875,
      0.93310546875,
      0.89794921875,
      1
    ]
  }
}